verifai/.DS_Store
verifai/__init__.py
verifai/client.py
verifai/error_table.py
verifai/falsifier.py
verifai/monitor.py
verifai/scenic_server.py
verifai/server.py
verifai/features/__init__.py
verifai/features/features.py
verifai/samplers/.DS_Store
verifai/samplers/__init__.py
verifai/samplers/bayesian_optimization.py
verifai/samplers/cross_entropy.py
verifai/samplers/dist_BO.py
verifai/samplers/domain_sampler.py
verifai/samplers/eg_sampler.py
verifai/samplers/feature_sampler.py
verifai/samplers/grid_sampler.py
verifai/samplers/halton.py
verifai/samplers/multi_armed_bandit.py
verifai/samplers/multi_objective.py
verifai/samplers/random_sampler.py
verifai/samplers/rejection.py
verifai/samplers/scenic_sampler.py
verifai/samplers/simulated_annealing.py
verifai/simulators/.DS_Store
verifai/simulators/__init__.py
verifai/simulators/car_simulator/.DS_Store
verifai/simulators/car_simulator/__init__.py
verifai/simulators/car_simulator/car_dynamics.py
verifai/simulators/car_simulator/car_object.py
verifai/simulators/car_simulator/client_car_sim.py
verifai/simulators/car_simulator/lane.py
verifai/simulators/car_simulator/simulator.py
verifai/simulators/car_simulator/examples/.DS_Store
verifai/simulators/car_simulator/examples/__init__.py
verifai/simulators/car_simulator/examples/simple_control.py
verifai/simulators/car_simulator/examples/control_utils/LQR_computation.py
verifai/simulators/car_simulator/examples/control_utils/__init__.py
verifai/simulators/car_simulator/examples/lanekeeping_LQR/__init__.py
verifai/simulators/car_simulator/examples/lanekeeping_LQR/lanekeeping_falsifier.py
verifai/simulators/car_simulator/examples/lanekeeping_LQR/lanekeeping_simulation.py
verifai/simulators/car_simulator/imgs/car-blue.png
verifai/simulators/car_simulator/imgs/car-gray.png
verifai/simulators/car_simulator/imgs/car-orange.png
verifai/simulators/car_simulator/imgs/car-purple.png
verifai/simulators/car_simulator/imgs/car-red.png
verifai/simulators/car_simulator/imgs/car-white.png
verifai-2.1.0.dist-info/LICENSE
verifai-2.1.0.dist-info/WHEEL
verifai-2.1.0.dist-info/METADATA
verifai-2.1.0.dist-info/RECORD
