Metadata-Version: 2.1
Name: verifai
Version: 2.1.0
Summary: A toolkit for the formal design and analysis of systems that include artificial intelligence (AI) and machine learning (ML) components.
Author: Tommaso Dreossi, Shromona Ghosh, Hadi Ravanbakhsh, Marcell Vazquez-Chanlatte, Sanjit A. Seshia
Author-email: Daniel Fremont <dfremont@ucsc.edu>, Edward Kim <ek65@berkeley.edu>
Maintainer-email: Daniel Fremont <dfremont@ucsc.edu>, Edward Kim <ek65@berkeley.edu>
Requires-Python: >=3.8
Classifier: Operating System :: OS Independent
Classifier: Development Status :: 5 - Production/Stable
Classifier: License :: OSI Approved :: BSD License
Classifier: Programming Language :: Python :: 3
Requires-Dist: numpy ~= 1.21
Requires-Dist: scipy ~= 1.7
Requires-Dist: dotmap ~= 1.3
Requires-Dist: metric-temporal-logic >= 0.1.5
Requires-Dist: matplotlib ~= 3.2
Requires-Dist: easydict ~= 1.9
Requires-Dist: joblib ~= 1.2
Requires-Dist: dill >= 0.3.1
Requires-Dist: future >= 0.18.3
Requires-Dist: pandas ~= 1.3
Requires-Dist: scikit-learn ~= 1.0
Requires-Dist: pygame ~= 2.1
Requires-Dist: kmodes <= 0.10.2
Requires-Dist: scenic >= 2.1.0b1, <4
Requires-Dist: progressbar2 ~= 3.53
Requires-Dist: networkx >= 2.6
Requires-Dist: statsmodels >= 0.13.2
Requires-Dist: GPy ~= 1.9 ; extra == "bayesopt"
Requires-Dist: GPyOpt ~= 1.2 ; extra == "bayesopt"
Requires-Dist: verifai[test] ; extra == "dev"
Requires-Dist: tox ~= 3.14 ; extra == "dev"
Requires-Dist: sphinx >= 4.1.0, <6 ; extra == "dev"
Requires-Dist: sphinx-rtd-theme >= 0.5.2 ; extra == "dev"
Requires-Dist: sphinx-tabs ~= 3.4.1 ; extra == "dev"
Requires-Dist: recommonmark >= 0.6.0 ; extra == "dev"
Requires-Dist: tensorflow ~= 2.8 ; extra == "examples"
Requires-Dist: gym >= 0.22 ; extra == "examples"
Requires-Dist: pyglet ~= 1.5 ; extra == "examples"
Requires-Dist: opencv-python ~= 4.5 ; extra == "examples"
Requires-Dist: pillow ~= 9.3 ; extra == "examples"
Requires-Dist: pyproj ~= 3.0 ; extra == "examples" and ( python_version < "3.10")
Requires-Dist: pyproj ~= 3.3 ; extra == "examples" and ( python_version >= "3.10")
Requires-Dist: ray ~= 1.10 ; extra == "parallel"
Requires-Dist: pytest >= 6.2.5, <8 ; extra == "test"
Requires-Dist: pytest-randomly >= 3.2 ; extra == "test"
Project-URL: Documentation, https://verifai.readthedocs.io
Project-URL: Repository, https://github.com/BerkeleyLearnVerify/VerifAI
Provides-Extra: bayesopt
Provides-Extra: dev
Provides-Extra: examples
Provides-Extra: parallel
Provides-Extra: test
